discord/ext/components/__init__.py
discord/ext/components/receiver.py
discord/ext/components/responder.py
discord/ext/components/sender.py
dpy_components-0.4.2.dist-info/LICENSE
dpy_components-0.4.2.dist-info/METADATA
dpy_components-0.4.2.dist-info/WHEEL
dpy_components-0.4.2.dist-info/top_level.txt
dpy_components-0.4.2.dist-info/RECORD
