Metadata-Version: 2.1
Name: dpy-components
Version: 0.4.2
Summary: Component for discord.py
Home-page: https://github.com/sevenc-nanashi/dpy-components
Author: sevenc_nanashi
License: UNKNOWN
Project-URL: Bug Tracker, https://github.com/sevenc-nanashi/dpy-components/issues
Platform: UNKNOWN
Classifier: Programming Language :: Python :: 3.8
Classifier: Programming Language :: Python :: 3.9
Classifier: License :: OSI Approved :: MIT License
Classifier: Operating System :: OS Independent
Requires-Dist: discord.py (>=1.6.0)
